pagseguro/__init__.py
pagseguro/config.py
pagseguro/exceptions.py
pagseguro/parsers.py
pagseguro/utils.py
pagseguro-0.3.3.dist-info/METADATA
pagseguro-0.3.3.dist-info/RECORD
pagseguro-0.3.3.dist-info/WHEEL
pagseguro-0.3.3.dist-info/top_level.txt
